mirto_asip_manager/__init__.py
mirto_asip_manager/asip.py
mirto_asip_manager/asip_manager.py
mirto_asip_manager/mirto_robot.py
mirto_asip_manager/serialConnector.py
mirto_asip_manager/services.py
mirto_asip_manager/settings.py
mirto_asip_manager-1.0.5.dist-info/METADATA
mirto_asip_manager-1.0.5.dist-info/RECORD
mirto_asip_manager-1.0.5.dist-info/WHEEL
mirto_asip_manager-1.0.5.dist-info/top_level.txt
