Metadata-Version: 2.1
Name: mirto-asip-manager
Version: 1.0.5
Summary: Serial manager for Mirto robot services
Home-page: https://github.com/jarzab3/mirto_asip_manager
Author: Adam Jarzebak
Author-email: adam@jarzebak.eu
License: UNKNOWN
Platform: UNKNOWN
Classifier: Programming Language :: Python :: 3
Classifier: License :: OSI Approved :: MIT License
Classifier: Operating System :: OS Independent
